pyrpcd/__init__.py
pyrpcd/server.py
pyrpcd/share.py
pyrpcd-0.0.6.dist-info/METADATA
pyrpcd-0.0.6.dist-info/WHEEL
pyrpcd-0.0.6.dist-info/top_level.txt
pyrpcd-0.0.6.dist-info/RECORD
