Metadata-Version: 2.1
Name: pyrpcd
Version: 0.0.6
Summary: Run a RPC server by the most convenient way
Home-page: https://github.com/aiyojun/pysolv
Author: aiyojun
Author-email: aiyojun@gmail.com
Classifier: Programming Language :: Python :: 3
Requires-Python: >=3.6
Requires-Dist: tornado>=6.4.1
Requires-Dist: voxe==0.0.3
